Workbook

Sheet Full Report  JULY 25 Report
A1: AMNESTY INTERNATIONAL KENYA 2025 REPORT | C1: TOTAL BUDGET | D1: ACTUAL COSTS JULY 25 | E1: VARIANCE | F1: % SPENT | G1: Q1 BUDGET | H1: Q2 BUDGET | I1: Q3 BUDGET | J1: Q4 BUDGET
B3: REVENUE ANALYSIS 2025
B4: Balance b/f from 2024-estimates DEFICIT | C4: =-61380310/2 -> -30690155
B5: 2025 RAM Allocation | C5: 126000000
B6: FIF Allocation | C6: 9500000
B7: HEWLETT FOUNDATION | C7: 51658737
B8: BOTNAR | C8: ='[1]Aproved Budget 2025 .'!F9 -> 14929325
B9: RELIEF FUNDS
B10: HEINRICH BOLL FOUNDATION | C10: 7010000
B11: MEMBERSHIP
B12: INTEREST
B13: TOTAL REVENUE 2025 | C13: =SUM(C4:C12) -> 178407907 | D13: =D125 -> 107444960 | E13: =C13-D13 -> 70962947 | F13: =D13/C13 -> 0.60224326
B15: VARIANCE
B17: EXPENDITURE ALLOCATION 2025
A18: Budget Codes | B18: Result Areas
A19: 2100/000 | B19: Movement Building
A20: 2100/001 | B20: Events and workshops | C20: =#REF!+#REF!+#REF!+#REF! -> #REF! | D20: ='[1]Trail Bal. JULY 2025'!J52 -> 1908300 | E20: =C20-D20 -> #REF! | F20: =D20/C20 -> #REF! | G20: 900000 | H20: 800000 | I20: 700000 | J20: 600000
A21: 2100/002 | B21: Research, publications and tools | C21: =#REF!+#REF!+#REF!+#REF! -> #REF! | D21: 0 | E21: =C21-D21 -> #REF! | F21: =D21/C21 -> #REF! | G21: 750000 | H21: 0 | I21: 750000 | J21: 0
A22: 2100/003 | B22: National mission travel | C22: =#REF!+#REF!+#REF!+#REF! -> #REF! | D22: ='[1]Trail Bal. JULY 2025'!D54 -> 95700 | E22: =C22-D22 -> #REF! | F22: =D22/C22 -> #REF! | G22: 250000 | H22: 200000 | I22: 300000 | J22: 250000
A23: 2100/004 | B23: Project rapid response and mini grants | C23: =#REF!+#REF!+#REF!+#REF! -> #REF! | D23: 0 | E23: =C23-D23 -> #REF! | G23: 300000 | H23: 1000000 | I23: 1500000 | J23: 2000000
A24: 2100/005 | B24: Campaign Manager (Emily) | C24: =#REF!+#REF!+#REF!+#REF! -> #REF! | D24: ='[1]Trail Bal. JULY 2025'!D56 -> 3724378.1 | E24: =C24-D24 -> #REF! | F24: =D24/C24 -> #REF! | G24: =C24/4 -> #REF! | H24: =G24 -> #REF! | I24: =H24 -> #REF! | J24: =I24 -> #REF!
A25: 2100/006 | B25: Campaign Officer (James) | C25: =#REF!+#REF!+#REF!+#REF! -> #REF! | D25: ='[1]Trail Bal. JULY 2025'!D57-D32 -> 1903867.5 | E25: =C25-D25 -> #REF! | F25: =D25/C25 -> #REF! | G25: =C25/4 -> #REF! | H25: =G25 -> #REF! | I25: =H25 -> #REF! | J25: =I25 -> #REF!
A26: 2100/007 | B26: Campaign Officer (Amy) | C26: =#REF!+#REF!+#REF!+#REF! -> #REF! | D26: ='[1]Trail Bal. JULY 2025'!D58 -> 1825892 | E26: =C26-D26 -> #REF! | F26: =D26/C26 -> #REF! | G26: =C26/4 -> #REF! | H26: =G26 -> #REF! | I26: =H26 -> #REF! | J26: =I26 -> #REF!
A27: 2100/008 | B27: Impact Reporting Officer (vacant) 50% | C27: =#REF!+#REF!+#REF!+#REF! -> #REF! | D27: 0 | E27: =C27-D27 -> #REF! | G27: =C27/4 -> #REF! | H27: =G27 -> #REF! | I27: =H27 -> #REF! | J27: =I27 -> #REF!
A28: 2100/009 | B28: Monitoring, Evaluation & Learning | C28: =#REF!+#REF!+#REF!+#REF! -> #REF! | D28: ='[1]Trail Bal. JULY 2025'!J60 -> 442770 | E28: =C28-D28 -> #REF! | F28: =D28/C28 -> #REF! | G28: 250000 | H28: 100000 | I28: 300000 | J28: =C28-G28-H28-I28 -> #REF!
A29: 2100/010 | B29: Campaign Officer (Eunice) | C29: =#REF!+#REF!+#REF!+#REF! -> #REF! | D29: ='[1]Trail Bal. JULY 2025'!D61 -> 1197897.4 | E29: =C29-D29 -> #REF! | F29: =D29/C29 -> #REF! | G29: =C29/4 -> #REF! | H29: =G29 -> #REF! | I29: =H29 -> #REF! | J29: =I29 -> #REF!
A30: 2100/011 | B30: Membership | C30: =#REF!+#REF!+#REF!+#REF!-600000 -> #REF! | D30: ='[1]Trail Bal. JULY 2025'!D62-D31 -> 510234 | E30: =C30-D30 -> #REF! | F30: =D30/C30 -> #REF! | G30: 900000 | H30: 1000000 | I30: 1000000 | J30: 600000
A31: 2100/012 | B31: Merchandise | C31: =#REF!+#REF!+#REF!+#REF! -> #REF! | D31: 263716 | E31: =C31-D31 -> #REF! | F31: =D31/C31 -> #REF!
B32: Staff Gratuaity -James Kimila | D32: 613123 | F32: =D32/C32 -> #DIV/0!
B33: Total Movement Building | C33: =SUM(C20:C31) -> #REF! | D33: =SUM(D20:D32) -> 12485878 | E33: =SUM(E20:E31) -> #REF! | F33: =D33/C33 -> #REF! | G33: =SUM(G20:G30) -> #REF! | H33: =SUM(H20:H30) -> #REF! | I33: =SUM(I20:I30) -> #REF! | J33: =SUM(J20:J30) -> #REF! | K33: =D33-'[1]Trail Bal. JULY 2025'!J51 -> 0
A35: 2400/000 | B35: Equality and Anti-Discrimination
A36: 2400/001 | B36: Events and workshops | C36: =#REF!+#REF!+#REF!+#REF! -> #REF! | D36: ='[1]Trail Bal. JULY 2025'!D77 -> 538900 | E36: =C36-D36 -> #REF! | F36: =D36/C36 -> #REF! | G36: 1000000 | H36: 800000 | I36: 1000000 | J36: 500000
A37: 2400/002 | B37: Research, publications and tools | C37: =#REF!+#REF!+#REF!+#REF! -> #REF! | D37: ='[1]Trail Bal. JULY 2025'!D78 -> 616688 | E37: =C37-D37 -> #REF! | F37: =D37/C37 -> #REF! | G37: 200000 | H37: 250000 | I37: 500000 | J37: 550000
A38: 2400/003 | B38: National mission travel | C38: =#REF!+#REF!+#REF!+#REF! -> #REF! | D38: ='[1]Trail Bal. JULY 2025'!D79 -> 211710.02 | E38: =C38-D38 -> #REF! | F38: =D38/C38 -> #REF! | G38: 250000 | H38: 300000 | I38: 400000 | J38: 350000
A39: 2400/004 | B39: Project rapid response and mini grants | C39: =#REF!+#REF!+#REF!+#REF! -> #REF! | D39: ='[1]Trail Bal. JULY 2025'!D80 -> 126672 | E39: =C39-D39 -> #REF! | F39: =D39/C39 -> #REF! | G39: 400000 | H39: 600000 | I39: 1000000 | J39: 1000000
A40: 2400/005 | B40: Campaign Manager (Zaina) | C40: =#REF!+#REF!+#REF!+#REF! -> #REF! | D40: ='[1]Trail Bal. JULY 2025'!D81 -> 3164375.1 | E40: =C40-D40 -> #REF! | F40: =D40/C40 -> #REF! | G40: =C40/4 -> #REF! | H40: =G40 -> #REF! | I40: =H40 -> #REF! | J40: =I40 -> #REF!
A41: 2400/006 | B41: Campaign Officer (Gaudence) | C41: =#REF!+#REF!+#REF!+#REF! -> #REF! | D41: ='[1]Trail Bal. JULY 2025'!D82 -> 1279635.9 | E41: =C41-D41 -> #REF! | F41: =D41/C41 -> #REF! | G41: =C41/4 -> #REF! | H41: =G41 -> #REF! | I41: =H41 -> #REF! | J41: =I41 -> #REF!
B42: Total Equality and Anti-Discrimination | C42: =SUM(C36:C41) -> #REF! | D42: =SUM(D36:D41) -> 5937981.1 | E42: =SUM(E36:E41) -> #REF! | F42: =D42/C42 -> #REF! | G42: =SUM(G36:G41) -> #REF! | H42: =SUM(H36:H41) -> #REF! | I42: =SUM(I36:I41) -> #REF! | J42: =SUM(J36:J41) -> #REF!
A44: 2500/000 | B44: Civil Liberties
A45: 2500/001 | B45: Events and workshops | C45: =#REF!+#REF!+#REF!+#REF! -> #REF! | D45: ='[1]Trail Bal. JULY 2025'!J86 -> 192000 | E45: =C45-D45 -> #REF! | G45: 700000 | H45: 1700000 | I45: 1000000 | J45: 1600000
A46: 2500/002 | B46: Research, publications and tools | C46: =#REF!+#REF!+#REF!+#REF! -> #REF! | D46: ='[1]Trail Bal. JULY 2025'!J87 -> 455995 | E46: =C46-D46 -> #REF! | F46: =D46/C46 -> #REF! | G46: 300000 | H46: 500000 | I46: 400000 | J46: 400000
A47: 2500/003 | B47: National mission travel | C47: =#REF!+#REF!+#REF!+#REF! -> #REF! | D47: ='[1]Trail Bal. JULY 2025'!D88 -> 71145 | E47: =C47-D47 -> #REF! | F47: =D47/C47 -> #REF! | G47: 400000 | H47: 500000 | I47: 200000 | J47: 300000
A48: 2500/004 | B48: Project rapid response and mini grants | C48: =#REF!+#REF!+#REF!+#REF! -> #REF! | D48: ='[1]Trail Bal. JULY 2025'!D89 -> 277581 | E48: =C48-D48 -> #REF! | F48: =D48/C48 -> #REF! | G48: 500000 | H48: 600000 | I48: 1000000 | J48: 1300000
A49: 2500/005 | B49: Campaign Manager (Edward) | C49: =#REF!+#REF!+#REF!+#REF! -> #REF! | D49: ='[1]Trail Bal. JULY 2025'!D90 -> 3513918.6 | E49: =C49-D49 -> #REF! | F49: =D49/C49 -> #REF! | G49: =C49/4 -> #REF! | H49: =G49 -> #REF! | I49: =H49 -> #REF! | J49: =I49 -> #REF!
A50: 2500/006 | B50: Campaign Officer (Rajab) | C50: =#REF!+#REF!+#REF!+#REF! -> #REF! | D50: ='[1]Trail Bal. JULY 2025'!D91 -> 2068839.2 | E50: =C50-D50 -> #REF! | F50: =D50/C50 -> #REF! | G50: =C50/4 -> #REF! | H50: =G50 -> #REF! | I50: =H50 -> #REF! | J50: =I50 -> #REF!
A51: 2500/008 | B51: Research Officer (Benta) | C51: =#REF!+#REF!+#REF!+#REF! -> #REF! | D51: ='[1]Trail Bal. JULY 2025'!D113 -> 217535.36 | E51: =C51-D51 -> #REF! | F51: =D51/C51 -> #REF! | G51: =C51/4 -> #REF! | H51: =G51 -> #REF! | I51: =H51 -> #REF! | J51: =I51 -> #REF!
B52: Total Civil Liberties | C52: =SUM(C45:C51) -> #REF! | D52: =SUM(D45:D51) -> 6797014.3 | E52: =SUM(E45:E51) -> #REF! | F52: =D52/C52 -> #REF! | G52: =SUM(G45:G51) -> #REF! | H52: =SUM(H45:H51) -> #REF! | I52: =SUM(I45:I51) -> #REF! | J52: =SUM(J45:J51) -> #REF!
B54: Protection
A55: 2500/010 | B55: Project rapid response and mini grants | C55: =#REF!+#REF!+#REF!+#REF! -> #REF! | D55: 0 | E55: =C55-D55 -> #REF! | F55: =D55/C55 -> #REF! | G55: 0 | H55: 600000 | I55: 900000 | J55: 300000
A56: 2500/011 | B56: Protection Officer (Wangui) 50% | C56: =#REF!+#REF!+#REF!+#REF! -> #REF! | D56: ='[1]Trail Bal. JULY 2025'!D96 -> 755920.81 | E56: =C56-D56 -> #REF! | F56: =D56/C56 -> #REF! | G56: 0 | H56: =C56/3 -> #REF! | I56: =H56 -> #REF! | J56: =I56 -> #REF!
B57: Total Protection | C57: =SUM(C55:C56) -> #REF! | D57: =SUM(D55:D56) -> 755920.81 | E57: =SUM(E55:E56) -> #REF! | F57: =D57/C57 -> #REF! | G57: =SUM(G55:G56) -> 0 | H57: =SUM(H55:H56) -> #REF! | I57: =SUM(I55:I56) -> #REF! | J57: =SUM(J55:J56) -> #REF!
A59: 2900/000 | B59: Technology and Human Rights
A60: 2900/001 | B60: Events and workshops | C60: =#REF!+#REF!+#REF!+#REF! -> #REF! | D60: ='[1]Trail Bal. JULY 2025'!D163 -> 15101017 | E60: =C60-D60 -> #REF! | F60: =D60/C60 -> #REF! | G60: 5000000 | H60: 8000000 | I60: 8000000 | J60: 8000000
A61: 2900/002 | B61: Research, publications and tools | C61: =#REF!+#REF!+#REF!+#REF! -> #REF! | D61: ='[1]Trail Bal. JULY 2025'!D164 -> 1078090 | E61: =C61-D61 -> #REF! | F61: =D61/C61 -> #REF! | G61: 2000000 | H61: 1000000 | I61: 1500000 | J61: 1500000
A62: 2900/003 | B62: National mission travel | C62: =#REF!+#REF!+#REF!+#REF! -> #REF! | D62: ='[1]Trail Bal. JULY 2025'!D165 -> 485819 | E62: =C62-D62 -> #REF! | F62: =D62/C62 -> #REF! | G62: 1000000 | H62: 1500000 | I62: 2000000 | J62: =C62-G62-H62-I62 -> #REF!
A63: 2900/004 | B63: Project rapid response and mini grants | C63: =#REF!+#REF!+#REF!+#REF! -> #REF! | D63: 0 | E63: =C63-D63 -> #REF! | F63: =D63/C63 -> #REF! | G63: 100000 | H63: 150000 | I63: 100000 | J63: =C63-G63-H63-I63 -> #REF!
A64: 2900/005 | B64: Campaign Manager (Victor) | C64: =#REF!+#REF!+#REF!+#REF! -> #REF! | D64: ='[1]Trail Bal. JULY 2025'!D167 -> 3164375.1 | E64: =C64-D64 -> #REF! | F64: =D64/C64 -> #REF! | G64: =C64/4 -> #REF! | H64: =G64 -> #REF! | I64: =H64 -> #REF! | J64: =I64 -> #REF!
A65: 2900/006 | B65: Campaign Officer (Sharlene) | C65: =#REF!+#REF!+#REF!+#REF! -> #REF! | D65: ='[1]Trail Bal. JULY 2025'!D168 -> 1646138.2 | E65: =C65-D65 -> #REF! | F65: =D65/C65 -> #REF! | G65: =C65/4 -> #REF! | H65: =C65/4 -> #REF! | I65: =H65 -> #REF! | J65: =I65 -> #REF!
A66: 2900/007 | B66: Campaign Officer (Aurelia) | C66: =#REF!+#REF!+#REF!+#REF! -> #REF! | D66: ='[1]Trail Bal. JULY 2025'!D169 -> 1501601.7 | E66: =C66-D66 -> #REF! | F66: =D66/C66 -> #REF! | G66: =C66/4 -> #REF! | H66: =G66 -> #REF! | I66: =H66 -> #REF! | J66: =I66 -> #REF!
A67: 2900/008 | B67: Campaign Officer (Benta) | C67: =#REF!+#REF!+#REF!+#REF! -> #REF! | D67: ='[1]Trail Bal. JULY 2025'!D170 -> 1292252.2 | E67: =C67-D67 -> #REF! | F67: =D67/C67 -> #REF! | G67: =C67/4 -> #REF! | H67: =G67 -> #REF! | I67: =H67 -> #REF! | J67: =I67 -> #REF!
B68: Total Technology and Human Rights | C68: =SUM(C60:C67) -> #REF! | D68: =SUM(D60:D67) -> 24269293 | E68: =SUM(E60:E67) -> #REF! | F68: =D68/C68 -> #REF! | G68: =SUM(G60:G67) -> #REF! | H68: =SUM(H60:H67) -> #REF! | I68: =SUM(I60:I67) -> #REF! | J68: =SUM(J60:J67) -> #REF!
A70: 2600/000 | B70: Office of Executive Director
A71: 2600/002 | B71: National mission travel | C71: =#REF!+#REF!+#REF!+#REF! -> #REF! | D71: ='[1]Trail Bal. JULY 2025'!D105 -> 184510.58 | E71: =C71-D71 -> #REF! | F71: =D71/C71 -> #REF! | G71: 100000 | H71: 150000 | I71: 150000 | J71: 100000
A72: 2600/004 | B72: Staff international mission travel | C72: =#REF!+#REF!+#REF!+#REF! -> #REF! | D72: =-'[1]Trail Bal. JULY 2025'!F107 -> -151217.8 | E72: =C72-D72 -> #REF! | F72: =D72/C72 -> #REF! | G72: 0 | H72: 300000 | I72: 300000 | J72: 100000
A73: 2600/009 | B73: Quarterly Advisory board meetings | C73: =#REF!+#REF!+#REF!+#REF! -> #REF! | D73: ='[1]Trail Bal. JULY 2025'!J110 -> 663354.1 | E73: =C73-D73 -> #REF! | F73: =D73/C73 -> #REF! | G73: 250000 | H73: 250000 | I73: 250000 | J73: 250000
A74: 2600/003 | B74: Annual Delegates Conference | C74: =#REF!+#REF!+#REF!+#REF! -> #REF! | D74: ='[1]Trail Bal. JULY 2025'!D106 -> 6500 | E74: =C74-D74 -> #REF! | F74: =D74/C74 -> #REF! | G74: 0 | H74: 0 | I74: 4000000 | J74: 0
A75: 2600/010 | B75: Executive Director ( Irungu) | C75: =#REF!+#REF!+#REF!+#REF! -> #REF! | D75: ='[1]Trail Bal. JULY 2025'!D111 -> 8510425 | E75: =C75-D75 -> #REF! | F75: =D75/C75 -> #REF! | G75: =C75/4 -> #REF! | H75: =G75 -> #REF! | I75: =H75 -> #REF! | J75: =I75 -> #REF!
A76: 2600/011 | B76: Executive Officer (Irene) | C76: =#REF!+#REF!+#REF!+#REF! -> #REF! | D76: ='[1]Trail Bal. JULY 2025'!D112 -> 1765641.1 | E76: =C76-D76 -> #REF! | F76: =D76/C76 -> #REF! | G76: =C76/4 -> #REF! | H76: =G76 -> #REF! | I76: =H76 -> #REF! | J76: =I76 -> #REF!
A77: 2600/013 | B77: Interns | C77: =#REF!+#REF!+#REF!+#REF! -> #REF! | D77: ='[1]Trail Bal. JULY 2025'!D114 -> 239750 | E77: =C77-D77 -> #REF! | F77: 0 | G77: 200000 | H77: 200000 | I77: 200000 | J77: 200000
A78: 2600/015 | B78: Fundraising Manager (Florence) | C78: =#REF!+#REF!+#REF!+#REF!+#REF! -> #REF! | D78: ='[1]Trail Bal. JULY 2025'!D129 -> 3264721 | E78: =C78-D78 -> #REF! | F78: =D78/C78 -> #REF! | G78: =C78/4 -> #REF! | H78: =G78 -> #REF! | I78: =H78 -> #REF! | J78: =I78 -> #REF!
A79: 2600/016 | B79: Fundraising Costs | C79: =#REF!+#REF!+#REF!+#REF!+#REF! -> #REF! | D79: ='[1]Trail Bal. JULY 2025'!D130 -> 2855302.4 | E79: =C79-D79 -> #REF! | F79: =D79/C79 -> #REF! | G79: 1000000 | H79: 1500000 | I79: 1000000 | J79: =C79-G79-H79-I79 -> #REF!
B80: Total Office of Executive Director | C80: =SUM(C71:C79)+4436213 -> #REF! | D80: =SUM(D71:D79) -> 17338986 | E80: =SUM(E71:E79) -> #REF! | F80: =D80/C80 -> #REF! | G80: =SUM(G71:G79) -> #REF! | H80: =SUM(H71:H79) -> #REF! | I80: =SUM(I71:I79) -> #REF! | J80: =SUM(J71:J79) -> #REF!
B82: People and Diversity
A83: 2600/022 | B83: Employers Liability (EL) | C83: =#REF!+#REF!+#REF!+#REF! -> #REF! | D83: ='[1]Trail Bal. JULY 2025'!J122 -> 877603 | E83: =C83-D83 -> #REF! | F83: =D83/C83 -> #REF! | G83: 700000 | H83: 500000 | I83: 0 | J83: 0
A84: 2600/023 | B84: Annual staff capacity-building events | C84: =#REF!+#REF!+#REF!+#REF! -> #REF! | D84: ='[1]Trail Bal. JULY 2025'!D123 -> 194377.5 | E84: =C84-D84 -> #REF! | F84: =D84/C84 -> #REF! | G84: 250000 | H84: 250000 | I84: 250000 | J84: 250000
A85: 2600/024 | B85: Staff capacity-building fund | C85: =#REF!+#REF!+#REF!+#REF! -> #REF! | D85: ='[1]Trail Bal. JULY 2025'!J121 -> 590560 | E85: =C85-D85 -> #REF! | F85: =D85/C85 -> #REF! | G85: 2500000 | H85: 2000000 | I85: 1500000 | J85: 1200000
A86: 2600/025 | B86: Staff Welfare fund | C86: =#REF!+#REF!+#REF!+#REF! -> #REF! | D86: ='[1]Trail Bal. JULY 2025'!D125 -> 85300 | E86: =C86-D86 -> #REF! | F86: =D86/C86 -> #REF! | G86: 25000 | H86: 25000 | I86: 25000 | J86: 25000
A87: 2600/027 | B87: People & Diversity Manager (Cynthia) | C87: =#REF!+#REF!+#REF!+#REF! -> #REF! | D87: ='[1]Trail Bal. JULY 2025'!D127 -> 2729617.8 | E87: =C87-D87 -> #REF! | F87: =D87/C87 -> #REF! | G87: =C87/4 -> #REF! | H87: =G87 -> #REF! | I87: =H87 -> #REF! | J87: =I87 -> #REF!
A88: 2600/028 | B88: Annual Staff Medical Cover | C88: =#REF!+#REF!+#REF!+#REF! -> #REF! | D88: ='[1]Trail Bal. JULY 2025'!D128 -> 12995672 | E88: =C88-D88 -> #REF! | F88: =D88/C88 -> #REF! | G88: 11000000 | H88: 0 | I88: 0 | J88: 0
B89: Total People and Diversity | C89: =SUM(C83:C88) -> #REF! | D89: =SUM(D83:D88) -> 17473131 | E89: =SUM(E83:E88) -> #REF! | F89: =D89/C89 -> #REF! | G89: =SUM(G83:G88) -> #REF! | H89: =SUM(H83:H88) -> #REF! | I89: =SUM(I83:I88) -> #REF! | J89: =SUM(J83:J88) -> #REF!
A91: 2700/000 | B91: Finance and Administration
A92: 2700/004 | B92: Rent and Service Charge/RTO option/Investments | C92: =#REF!+#REF!+#REF!+#REF!+#REF! -> #REF! | D92: ='[1]Trail Bal. JULY 2025'!J132 -> 4734790.4 | E92: =C92-D92 -> #REF! | F92: =D92/C92 -> #REF! | G92: =C92/4 -> #REF! | H92: =G92 -> #REF! | I92: =H92 -> #REF! | J92: =I92 -> #REF!
A93: 2700/005 | B93: Telephone / Internet | C93: =#REF!+#REF!+#REF!+#REF!+#REF! -> #REF! | D93: ='[1]Trail Bal. JULY 2025'!D133 -> 798671.17 | E93: =C93-D93 -> #REF! | F93: =D93/C93 -> #REF! | G93: =C93/4 -> #REF! | H93: =G93 -> #REF! | I93: =H93 -> #REF! | J93: =I93 -> #REF!
A94: 2700/006 | B94: Stationery | C94: =#REF!+#REF!+#REF!+#REF!+#REF! -> #REF! | D94: ='[1]Trail Bal. JULY 2025'!D134 -> 51295.2 | E94: =C94-D94 -> #REF! | F94: =D94/C94 -> #REF! | G94: =C94/4 -> #REF! | H94: =G94 -> #REF! | I94: =H94 -> #REF! | J94: =I94 -> #REF!
A95: 2700/007 | B95: Subscriptions (magazines newspapers) | C95: =#REF!+#REF!+#REF!+#REF!+#REF! -> #REF! | D95: 0 | E95: =C95-D95 -> #REF! | G95: =C95/4 -> #REF! | H95: =G95 -> #REF! | I95: =H95 -> #REF! | J95: =I95 -> #REF!
A96: 2700/008 | B96: Printer Lease | C96: =#REF!+#REF!+#REF!+#REF!+#REF! -> #REF! | D96: ='[1]Trail Bal. JULY 2025'!D136 -> 62596 | E96: =C96-D96 -> #REF! | F96: =D96/C96 -> #REF! | G96: =C96/4 -> #REF! | H96: =G96 -> #REF! | I96: =H96 -> #REF! | J96: =I96 -> #REF!
A97: 2700/009 | B97: IT support & Maintenance | C97: =#REF!+#REF!+#REF!+#REF!+#REF! -> #REF! | D97: ='[1]Trail Bal. JULY 2025'!D137 -> 69600 | E97: =C97-D97 -> #REF! | F97: =D97/C97 -> #REF! | G97: =C97/4 -> #REF! | H97: =G97 -> #REF! | I97: =H97 -> #REF! | J97: =I97 -> #REF!
A98: 2700/010 | B98: Program Sundries (Guest and Staff teas) | C98: =#REF!+#REF!+#REF!+#REF! -> #REF! | D98: ='[1]Trail Bal. JULY 2025'!D138 -> 234710 | E98: =C98-D98 -> #REF! | G98: =C98/4 -> #REF! | H98: =G98 -> #REF! | I98: =H98 -> #REF! | J98: =I98 -> #REF!
A99: 2700/011 | B99: Office equipment Purchase/repairs/maintenance | C99: =#REF!+#REF!+#REF!+#REF! -> #REF! | D99: ='[1]Trail Bal. JULY 2025'!D139 -> 325623.52 | E99: =C99-D99 -> #REF! | F99: =D99/C99 -> #REF! | G99: =C99/4 -> #REF! | H99: =G99 -> #REF! | I99: =H99 -> #REF! | J99: =I99 -> #REF!
A100: 2700/012 | B100: Audit Costs | C100: =#REF!+#REF!+#REF!+#REF! -> #REF! | D100: ='[1]Trail Bal. JULY 2025'!J140 -> 88000 | E100: =C100-D100 -> #REF! | F100: =D100/C100 -> #REF! | G100: 0 | H100: 900000 | I100: 0 | J100: =I100 -> 0
A101: 2700/013 | B101: Bank Charges | C101: =#REF!+#REF!+#REF!+#REF! -> #REF! | D101: ='[1]Trail Bal. JULY 2025'!D141 -> 343068.52 | E101: =C101-D101 -> #REF! | F101: =D101/C101 -> #REF! | G101: =C101/4 -> #REF! | H101: =G101 -> #REF! | I101: =H101 -> #REF! | J101: =I101 -> #REF!
A102: 2700/014 | B102: Utility Bills / Electricity | C102: =#REF!+#REF!+#REF!+#REF! -> #REF! | D102: ='[1]Trail Bal. JULY 2025'!J142 -> 549695.75 | E102: =C102-D102 -> #REF! | F102: =D102/C102 -> #REF! | G102: =C102/4 -> #REF! | H102: =G102 -> #REF! | I102: =H102 -> #REF! | J102: =I102 -> #REF!
A103: 2700/015 | B103: Office Cleaning and garbage collection | C103: =#REF!+#REF!+#REF!+#REF! -> #REF! | D103: ='[1]Trail Bal. JULY 2025'!J143 -> 60000 | E103: =C103-D103 -> #REF! | F103: =D103/C103 -> #REF! | G103: =C103/4 -> #REF! | H103: =G103 -> #REF! | I103: =H103 -> #REF! | J103: =I103 -> #REF!
A104: 2700/016 | B104: Mail and Courier | C104: =#REF!+#REF!+#REF!+#REF! -> #REF! | D104: ='[1]Trail Bal. JULY 2025'!D144 -> 50300 | E104: =C104-D104 -> #REF! | F104: =D104/C104 -> #REF! | G104: =C104/4 -> #REF! | H104: =G104 -> #REF! | I104: =H104 -> #REF! | J104: =I104 -> #REF!
A105: 2700/017 | B105: Local Travel | C105: =#REF!+#REF!+#REF!+#REF! -> #REF! | D105: ='[1]Trail Bal. JULY 2025'!D145 -> 945726.94 | E105: =C105-D105 -> #REF! | F105: =D105/C105 -> #REF! | G105: =C105/4 -> #REF! | H105: =G105 -> #REF! | I105: =H105 -> #REF! | J105: =I105 -> #REF!
A106: 2700/018 | B106: Out of Nairobi Travel | C106: =#REF!+#REF!+#REF!+#REF! -> #REF! | D106: 0 | E106: =C106-D106 -> #REF! | F106: =D106/C106 -> #REF! | G106: =C106/4 -> #REF! | H106: =G106 -> #REF! | I106: =H106 -> #REF! | J106: =I106 -> #REF!
A107: 2700/019 | B107: Softwares and Intangible Assets | C107: =#REF!+#REF!+#REF!+#REF! -> #REF! | D107: ='[1]Trail Bal. JULY 2025'!D147 -> 2145876.2 | E107: =C107-D107 -> #REF! | F107: =D107/C107 -> #REF! | G107: 1900000 | H107: 1000000 | I107: 800000 | J107: 1100000
A108: 2700/020 | B108: Finance and Administration Manager (Francis) | C108: =#REF!+#REF!+#REF!+#REF! -> #REF! | D108: ='[1]Trail Bal. JULY 2025'!D148 -> 3421520 | E108: =C108-D108 -> #REF! | F108: =D108/C108 -> #REF! | G108: =C108/4 -> #REF! | H108: =G108 -> #REF! | I108: =H108 -> #REF! | J108: =I108 -> #REF!
A109: 2700/021 | B109: Finance and Administration Officer (Stephen) | C109: =#REF!+#REF!+#REF!+#REF! -> #REF! | D109: ='[1]Trail Bal. JULY 2025'!D149 -> 2473447.6 | E109: =C109-D109 -> #REF! | F109: =D109/C109 -> #REF! | G109: =C109/4 -> #REF! | H109: =G109 -> #REF! | I109: =H109 -> #REF! | J109: =I109 -> #REF!
A110: 2700/022 | B110: Administrative Assistant (Ann) 50% | C110: =#REF!+#REF!+#REF!+#REF! -> #REF! | D110: ='[1]Trail Bal. JULY 2025'!D150 -> 422289.25 | E110: =C110-D110 -> #REF! | F110: =D110/C110 -> #REF! | G110: =C110/4 -> #REF! | H110: =G110 -> #REF! | I110: =H110 -> #REF! | J110: =I110 -> #REF!
...

Sheet Trial Bal&Budget 2025
A1: Trial Balance/Budget
L2: 9/4/2025 9:33 AM
L3: Page 1 / 1
L6: FKIBUE
A7: Period: 01/01/25..07/31/25
A11: AMNESTY INTERNATIONAL KENYA
A14: Budget Filter: 2025BUDGET
A15: G/L Account: Date Filter: 01/01/25..07/31/25, Budget Filter: 2025BUDGET
D17: Net Change | N17: Balance
A19: No. | B19: Name | D19: Debit | F19: Credit | H19: % of | K19: Budget | N19: Debit | P19: Credit | R19: % of | T19: Budget
A23: 1000/000 | B23: Income Statement
A24: 1000/020 | B24: Total Revenue | F24: 1.6034821e+08 | P24: 1.6034821e+08
A25: 1000/050 | B25: TOTAL FUNDING | F25: 1.6034821e+08 | P25: 1.6034821e+08
A26: 1000/100 | B26: RAM FUNDS | F26: 1.3622817e+08 | P26: 1.3622817e+08
A27: 1000/200 | B27: PORTICUS
A28: 1000/300 | B28: COMIC RELIEF
A29: 1000/400 | B29: MEMBERSHIP FEES | F29: 315120.25 | P29: 315120.25
A30: 1000/500 | B30: MERCHANDISE AND RETAIL | F30: 80352 | P30: 80352
A31: 1000/600 | B31: RELIEF FUNDS | F31: 1820452.1 | P31: 1820452.1
A32: 1000/700 | B32: FOREST PEOPLE PROGRAMME
A33: 1000/800 | B33: UNDP KENYA
A34: 1000/900 | B34: HEWLETT FOUNDATION
A35: 1100/000 | B35: FORD FOUNDATION
A36: 1100/100 | B36: MUSIC AFRICA FOUNDATION
A37: 1100/200 | B37: BOTNAR FOUNDATION | F37: 16338550 | P37: 16338550
A38: 1100/300 | B38: GIZ
A39: 1100/400 | B39: SWISS EMBASSY
A40: 1100/500 | B40: ROYAL EMBASSY OF NORWAY
A41: 1100/600 | B41: HEINRICH BOLL FOUNDATION | F41: 4907000 | P41: 4907000
A42: 1100/700 | B42: AMNESTY INTERNATIONAL UK SECTION
A43: 1100/800 | B43: German Grant
A44: 1200/000 | B44: UN-OHCHR
A45: 1500/000 | B45: INCOME - OTHER SPECIAL PROGRAMS
A46: 1600/000 | B46: INVESTMENT & BANK INTEREST | F46: 497934.92 | P46: 497934.92
A47: 1700/000 | B47: FOREIGN CURRENCY EXCHANGE GAIN
A48: 1700/100 | B48: UNREALISED EXCHANGE GAIN | F48: 65670.13 | P48: 65670.13
A49: 1800/000 | B49: DONATIONS | F49: 94960 | P49: 94960
A50: 2000/000 | B50: Total Expenditure | D50: 1.0747235e+08 | H50: 58.12992 | K50: 1.8488302e+08 | N50: 1.0747235e+08 | R50: 58.12992 | T50: 1.8488302e+08
A51: 2100/000 | B51: RESULT 1- HRE AND ACTIVISM | D51: 12485878 | H51: 81.001929 | K51: 15414297 | N51: 12485878 | R51: 81.001929 | T51: 15414297
A52: 2100/001 | B52: Events and Workshops | D52: 1908300 | H52: 133.44755 | K52: 1430000 | N52: 1908300 | R52: 133.44755 | T52: 1430000
A53: 2100/002 | B53: Research Publications and Tools | K53: 150000 | T53: 150000
A54: 2100/003 | B54: National Mission Travel | D54: 95700 | H54: 29.90625 | K54: 320000 | N54: 95700 | R54: 29.90625 | T54: 320000
A55: 2100/004 | B55: Project rapid response and mini grants
A56: 2100/005 | B56: Campaign Manager | D56: 3724378.1 | H56: 77.022926 | K56: 4835415.1 | N56: 3724378.1 | R56: 77.022926 | T56: 4835415.1
A57: 2100/006 | B57: Campaign Officer 1 | D57: 2516990.5 | H57: 101.20038 | K57: 2487135.4 | N57: 2516990.5 | R57: 101.20038 | T57: 2487135.4
A58: 2100/007 | B58: Campaign Officer 2 | D58: 1825892 | H58: 76.114939 | K58: 2398861.5 | N58: 1825892 | R58: 76.114939 | T58: 2398861.5
A59: 2100/008 | B59: Impact Reporting Officer
A60: 2100/009 | B60: Monitoring, Evaluation & Learning | D60: 442770 | H60: 88.554 | K60: 500000 | N60: 442770 | R60: 88.554 | T60: 500000
A61: 2100/010 | B61: Campaign Officer 3 | D61: 1197897.4 | H61: 75.202995 | K61: 1592885.2 | N61: 1197897.4 | R61: 75.202995 | T61: 1592885.2
A62: 2100/011 | B62: Movement Growth | D62: 773950 | H62: 45.526471 | K62: 1700000 | N62: 773950 | R62: 45.526471 | T62: 1700000
A63: 2200/000 | B63: RESULT 2- RIGHT TO ASSOCIATION
A64: 2200/001 | B64: Events and workshops
A65: 2200/002 | B65: Research publications and tools
A66: 2200/003 | B66: National Mission Travel
A67: 2200/004 | B67: Project rapid response and mini grants
A68: 2300/000 | B68: RESULT 3- RIGHT TO HEALTH
A69: 2300/001 | B69: Events and workshops
A70: 2300/002 | B70: Research publications and tools
A71: 2300/003 | B71: National mission travel
A72: 2300/004 | B72: Project rapid response and mini grants
A73: 2300/005 | B73: Campaign Manager
A74: 2300/006 | B74: Campaign Officer
A75: 2300/007 | B75: Campaign Intern
A76: 2400/000 | B76: RESULT 4- INEQUALITIES AND DISCRIMINATION | D76: 5937981.1 | H76: 58.29145 | K76: 10186710 | N76: 5937981.1 | R76: 58.29145 | T76: 10186710
A77: 2400/001 | B77: Events and workshops | D77: 538900 | H77: 182.67797 | K77: 295000 | N77: 538900 | R77: 182.67797 | T77: 295000
A78: 2400/002 | B78: Research publications and tools | D78: 616688 | H78: 32.219854 | K78: 1914000 | N78: 616688 | R78: 32.219854 | T78: 1914000
A79: 2400/003 | B79: National mission travel | D79: 211710.02 | H79: 88.212508 | K79: 240000 | N79: 211710.02 | R79: 88.212508 | T79: 240000
A80: 2400/004 | B80: Project rapid response and mini grants | D80: 126672 | H80: 22.989474 | K80: 551000 | N80: 126672 | R80: 22.989474 | T80: 551000
A81: 2400/005 | B81: Campaign Manager | D81: 3164375.1 | H81: 57.650142 | K81: 5488928.6 | N81: 3164375.1 | R81: 57.650142 | T81: 5488928.6
A82: 2400/006 | B82: Campaign Officer 1 | D82: 1279635.9 | H82: 75.371055 | K82: 1697781.6 | N82: 1279635.9 | R82: 75.371055 | T82: 1697781.6
A83: 2400/007 | B83: Campaign Officer 2
A84: 2400/008 | B84: COMIC RELEF ACTIVITIES B/F
A85: 2500/000 | B85: RESULT 5- FREEDOMS AND CITIZENSHIP | D85: 7335399.7 | H85: 64.905774 | K85: 11301614 | N85: 7335399.7 | R85: 64.905774 | T85: 11301614
A86: 2500/001 | B86: Events and workshops | D86: 192000 | N86: 192000
A87: 2500/002 | B87: Research publications and tools | D87: 455995 | H87: 91.199 | K87: 500000 | N87: 455995 | R87: 91.199 | T87: 500000
A88: 2500/003 | B88: National mission travel | D88: 71145 | H88: 7.1145 | K88: 1000000 | N88: 71145 | R88: 7.1145 | T88: 1000000
A89: 2500/004 | B89: Project rapid response and mini grants | D89: 277581 | H89: 55.5162 | K89: 500000 | N89: 277581 | R89: 55.5162 | T89: 500000
A90: 2500/005 | B90: Campaign Manager | D90: 3513918.6 | H90: 79.02271 | K90: 4446720 | N90: 3513918.6 | R90: 79.02271 | T90: 4446720
A91: 2500/006 | B91: Campaign Officer | D91: 2068839.2 | H91: 73.123149 | K91: 2829253.5 | N91: 2068839.2 | R91: 73.123149 | T91: 2829253.5
A92: 2500/007 | B92: Events and Workshop- Protection
A93: 2500/008 | B93: Research publications and Tools - Protection
A94: 2500/009 | B94: National mission travel - Protection
A95: 2500/010 | B95: Project rapid response and mini grants - Protection | K95: 1000000 | T95: 1000000
A96: 2500/011 | B96: Protection Officer - Protection | D96: 755920.81 | H96: 73.702353 | K96: 1025640 | N96: 755920.81 | R96: 73.702353 | T96: 1025640
A97: 2500/012 | B97: Events and workshops - Digital Rights
A98: 2500/013 | B98: Research, publications and tools - Digital Rights
A99: 2500/014 | B99: National mission travel - Digital Rights
A100: 2500/015 | B100: Project rapid response and mini grants - Digital Rights
A101: 2500/016 | B101: Campaign Officer- Digital Rights
A102: 2500/017 | B102: Campaign Officer 2- Digital Rights
A103: 2600/000 | B103: RESULT 6- OFFICE OF EXECUTIVE DIRECTOR | D103: 36248268 | H103: 63.895905 | K103: 56730190 | N103: 36248268 | R103: 63.895905 | T103: 56730190
A104: 2600/001 | B104: Events and Workshops
A105: 2600/002 | B105: National Mission Travel | D105: 192510.58 | H105: 16.042548 | K105: 1200000 | N105: 192510.58 | R105: 16.042548 | T105: 1200000
A106: 2600/003 | B106: Annual Delegates Conference | D106: 6500 | H106: 1.3 | K106: 500000 | N106: 6500 | R106: 1.3 | T106: 500000
A107: 2600/004 | B107: Staff International Mission Travel | F107: 151217.8 | H107: -75.6089 | K107: 200000 | P107: 151217.8 | R107: -75.6089 | T107: 200000
A108: 2600/007 | B108: Opinion Polls
A109: 2600/008 | B109: Monitoring Evaluation and Learning
A110: 2600/009 | B110: Quartely Advisory Board Meetings | D110: 660780.1 | H110: 132.15602 | K110: 500000 | N110: 660780.1 | R110: 132.15602 | T110: 500000
A111: 2600/010 | B111: Executive Director | D111: 8510425 | H111: 70.72597 | K111: 12032956 | N111: 8510425 | R111: 70.72597 | T111: 12032956
A112: 2600/011 | B112: Executive Officer | D112: 1765641.1 | H112: 76.054897 | K112: 2321535 | N112: 1765641.1 | R112: 76.054897 | T112: 2321535
...

Sheet Trail Bal. JULY 2025
A1: Trial Balance
H3: Wednesday, August 6, 2025
H4: Page 1 / 1
H7: FKIBUE
A8: Period: 01/01/25..07/31/25
A11: AMNESTY INTERNATIONAL KENYA
A15: G/L Account: Date Filter: 01/01/25..07/31/25
D17: Net Change | J17: Balance
A19: No. | B19: Name | D19: Debit | F19: Credit | J19: Debit | L19: Credit
A23: 1000/000 | B23: Income Statement
A24: 1000/020 | B24: Total Revenue | F24: 1.6031981e+08 | L24: 1.6031981e+08
A25: 1000/050 | B25: TOTAL FUNDING | F25: 1.6031981e+08 | L25: 1.6031981e+08
A26: 1000/100 | B26: RAM FUNDS | F26: 1.3622817e+08 | L26: 1.3622817e+08
A27: 1000/200 | B27: PORTICUS
A28: 1000/300 | B28: COMIC RELIEF
A29: 1000/400 | B29: MEMBERSHIP FEES | F29: 313987.5 | L29: 313987.5
A30: 1000/500 | B30: MERCHANDISE AND RETAIL | F30: 80352 | L30: 80352
A31: 1000/600 | B31: RELIEF FUNDS | F31: 1820452.1 | L31: 1820452.1
A32: 1000/700 | B32: FOREST PEOPLE PROGRAMME
A33: 1000/800 | B33: UNDP KENYA
A34: 1000/900 | B34: HEWLETT FOUNDATION
A35: 1100/000 | B35: FORD FOUNDATION
A36: 1100/100 | B36: MUSIC AFRICA FOUNDATION
A37: 1100/200 | B37: BOTNAR FOUNDATION | F37: 16338550 | L37: 16338550
A38: 1100/300 | B38: GIZ
A39: 1100/400 | B39: SWISS EMBASSY
A40: 1100/500 | B40: ROYAL EMBASSY OF NORWAY
A41: 1100/600 | B41: HEINRICH BOLL FOUNDATION | F41: 4907000 | L41: 4907000
A42: 1100/700 | B42: AMNESTY INTERNATIONAL UK SECTION
A43: 1100/800 | B43: German Grant
A44: 1200/000 | B44: UN-OHCHR
A45: 1500/000 | B45: INCOME - OTHER SPECIAL PROGRAMS
A46: 1600/000 | B46: INVESTMENT & BANK INTEREST | F46: 470671.75 | L46: 470671.75
A47: 1700/000 | B47: FOREIGN CURRENCY EXCHANGE GAIN
A48: 1700/100 | B48: UNREALISED EXCHANGE GAIN | F48: 65670.13 | L48: 65670.13
A49: 1800/000 | B49: DONATIONS | F49: 94960 | L49: 94960
A50: 2000/000 | B50: Total Expenditure | D50: 107444960 | J50: 107444960
A51: 2100/000 | B51: RESULT 1- HRE AND ACTIVISM | D51: 12485878 | J51: 12485878
A52: 2100/001 | B52: Events and Workshops | D52: 1908300 | J52: 1908300
A53: 2100/002 | B53: Research Publications and Tools
A54: 2100/003 | B54: National Mission Travel | D54: 95700 | J54: 95700
A55: 2100/004 | B55: Project rapid response and mini grants
A56: 2100/005 | B56: Campaign Manager | D56: 3724378.1 | J56: 3724378.1
A57: 2100/006 | B57: Campaign Officer 1 | D57: 2516990.5 | J57: 2516990.5
A58: 2100/007 | B58: Campaign Officer 2 | D58: 1825892 | J58: 1825892
A59: 2100/008 | B59: Impact Reporting Officer
A60: 2100/009 | B60: Monitoring, Evaluation & Learning | D60: 442770 | J60: 442770
A61: 2100/010 | B61: Campaign Officer 3 | D61: 1197897.4 | J61: 1197897.4
A62: 2100/011 | B62: Movement Growth | D62: 773950 | J62: 773950
A63: 2200/000 | B63: RESULT 2- RIGHT TO ASSOCIATION
A64: 2200/001 | B64: Events and workshops
A65: 2200/002 | B65: Research publications and tools
A66: 2200/003 | B66: National Mission Travel
A67: 2200/004 | B67: Project rapid response and mini grants
A68: 2300/000 | B68: RESULT 3- RIGHT TO HEALTH
A69: 2300/001 | B69: Events and workshops
A70: 2300/002 | B70: Research publications and tools
A71: 2300/003 | B71: National mission travel
A72: 2300/004 | B72: Project rapid response and mini grants
A73: 2300/005 | B73: Campaign Manager
A74: 2300/006 | B74: Campaign Officer
A75: 2300/007 | B75: Campaign Intern
A76: 2400/000 | B76: RESULT 4- INEQUALITIES AND DISCRIMINATION | D76: 5937981.1 | J76: 5937981.1
A77: 2400/001 | B77: Events and workshops | D77: 538900 | J77: 538900
A78: 2400/002 | B78: Research publications and tools | D78: 616688 | J78: 616688
A79: 2400/003 | B79: National mission travel | D79: 211710.02 | J79: 211710.02
A80: 2400/004 | B80: Project rapid response and mini grants | D80: 126672 | J80: 126672
A81: 2400/005 | B81: Campaign Manager | D81: 3164375.1 | J81: 3164375.1
A82: 2400/006 | B82: Campaign Officer 1 | D82: 1279635.9 | J82: 1279635.9
A83: 2400/007 | B83: Campaign Officer 2
A84: 2400/008 | B84: COMIC RELEF ACTIVITIES B/F
A85: 2500/000 | B85: RESULT 5- FREEDOMS AND CITIZENSHIP | D85: 7335399.7 | J85: 7335399.7
A86: 2500/001 | B86: Events and workshops | D86: 192000 | J86: 192000
A87: 2500/002 | B87: Research publications and tools | D87: 455995 | J87: 455995
A88: 2500/003 | B88: National mission travel | D88: 71145 | J88: 71145
A89: 2500/004 | B89: Project rapid response and mini grants | D89: 277581 | J89: 277581
A90: 2500/005 | B90: Campaign Manager | D90: 3513918.6 | J90: 3513918.6
A91: 2500/006 | B91: Campaign Officer | D91: 2068839.2 | J91: 2068839.2
A92: 2500/007 | B92: Events and Workshop- Protection
A93: 2500/008 | B93: Research publications and Tools - Protection
A94: 2500/009 | B94: National mission travel - Protection
A95: 2500/010 | B95: Project rapid response and mini grants - Protection
A96: 2500/011 | B96: Protection Officer - Protection | D96: 755920.81 | J96: 755920.81
A97: 2500/012 | B97: Events and workshops - Digital Rights
A98: 2500/013 | B98: Research, publications and tools - Digital Rights
A99: 2500/014 | B99: National mission travel - Digital Rights
A100: 2500/015 | B100: Project rapid response and mini grants - Digital Rights
A101: 2500/016 | B101: Campaign Officer- Digital Rights
A102: 2500/017 | B102: Campaign Officer 2- Digital Rights
A103: 2600/000 | B103: RESULT 6- OFFICE OF EXECUTIVE DIRECTOR | D103: 36255642 | J103: 36255642
A104: 2600/001 | B104: Events and Workshops
A105: 2600/002 | B105: National Mission Travel | D105: 184510.58 | J105: 184510.58
A106: 2600/003 | B106: Annual Delegates Conference | D106: 6500 | J106: 6500
A107: 2600/004 | B107: Staff International Mission Travel | F107: 151217.8 | L107: 151217.8
A108: 2600/007 | B108: Opinion Polls
A109: 2600/008 | B109: Monitoring Evaluation and Learning
A110: 2600/009 | B110: Quartely Advisory Board Meetings | D110: 663354.1 | J110: 663354.1
A111: 2600/010 | B111: Executive Director | D111: 8510425 | J111: 8510425
A112: 2600/011 | B112: Executive Officer | D112: 1765641.1 | J112: 1765641.1
A113: 2600/012 | B113: Research Officer | D113: 217535.36 | J113: 217535.36
...
